genice_svg/__init__.py
genice_svg/hooks.py
genice_svg/render_png.py
genice_svg/render_svg.py
genice_svg/formats/__init__.py
genice_svg/formats/png.py
genice_svg/formats/svg.py
genice_svg-0.6.1.dist-info/METADATA
genice_svg-0.6.1.dist-info/WHEEL
genice_svg-0.6.1.dist-info/entry_points.txt
genice_svg-0.6.1.dist-info/top_level.txt
genice_svg-0.6.1.dist-info/RECORD
