Metadata-Version: 2.1
Name: genice-svg
Version: 0.6.1
Summary: SVG format plugin for GenIce.
Home-page: https://github.com/vitroid/genice-svg/
Author: Masakazu Matsumoto
Author-email: vitroid@gmail.com
License: MIT
Keywords: genice,SVG
Platform: UNKNOWN
Classifier: Development Status :: 4 - Beta
Classifier: Intended Audience :: Developers
Classifier: Programming Language :: Python
Classifier: Programming Language :: Python :: 3.5
Requires-Dist: svgwrite
Requires-Dist: genice (<2.0)
Requires-Dist: pillow
Requires-Dist: attrdict
Requires-Dist: countrings (>=0.1.7)
Requires-Dist: jinja2
